audacityDiscogsExporter/__init__.py
audacityDiscogsExporter/__main__.py
audacityDiscogsExporter-0.1.0.dist-info/LICENSE
audacityDiscogsExporter-0.1.0.dist-info/METADATA
audacityDiscogsExporter-0.1.0.dist-info/WHEEL
audacityDiscogsExporter-0.1.0.dist-info/top_level.txt
audacityDiscogsExporter-0.1.0.dist-info/RECORD
